techdocs/__init__.py
techdocs/cli.py
techdocs/dtypes.py
techdocs/ops.py
techdocs/signatures/subcommand_signatures.json
techdocs/utils/LoggingManager.py
techdocs/utils/__init__.py
techdocs/utils/functools.py
techdocs/utils/parse.py
techdocs-0.2.2.data/data/subcommand_signatures.json
techdocs-0.2.2.dist-info/METADATA
techdocs-0.2.2.dist-info/WHEEL
techdocs-0.2.2.dist-info/entry_points.txt
techdocs-0.2.2.dist-info/top_level.txt
techdocs-0.2.2.dist-info/RECORD
