Metadata-Version: 2.1
Name: techdocs
Version: 0.2.2
Summary: Code documentation generation CLI App
Author-email: test <alfatrion123@gmail.com>
Requires-Python: >=3.10
Requires-Dist: requests
